Topsis_Kunal_102303330/__init__.py
Topsis_Kunal_102303330/topsis.py
topsis_kunal_102303330-1.0.1.dist-info/METADATA
topsis_kunal_102303330-1.0.1.dist-info/WHEEL
topsis_kunal_102303330-1.0.1.dist-info/entry_points.txt
topsis_kunal_102303330-1.0.1.dist-info/top_level.txt
topsis_kunal_102303330-1.0.1.dist-info/RECORD
