Metadata-Version: 2.4
Name: Topsis-Kunal-102303330
Version: 1.0.1
Summary: A Python package for TOPSIS decision making
Author-email: Kunal Sharma <kunalkomal1710@gmail.com>
License: MIT
Requires-Dist: pandas
Requires-Dist: numpy
